dytb/__init__.py
dytb/evaluate.py
dytb/train.py
dytb/evaluators/AutoencoderEvaluator.py
dytb/evaluators/ClassifierEvaluator.py
dytb/evaluators/DetectorEvaluator.py
dytb/evaluators/Evaluator.py
dytb/evaluators/Metric.py
dytb/evaluators/RegressorEvaluator.py
dytb/evaluators/__init__.py
dytb/evaluators/metrics.py
dytb/inputs/__init__.py
dytb/inputs/images.py
dytb/inputs/interfaces.py
dytb/inputs/processing.py
dytb/inputs/predefined/Cifar10.py
dytb/inputs/predefined/Cifar100.py
dytb/inputs/predefined/MNIST.py
dytb/inputs/predefined/ORLFaces.py
dytb/inputs/predefined/PASCALVOC2012Classification.py
dytb/inputs/predefined/PASCALVOC2012Localization.py
dytb/inputs/predefined/__init__.py
dytb/models/__init__.py
dytb/models/collections.py
dytb/models/interfaces.py
dytb/models/layers.py
dytb/models/utils.py
dytb/models/visualization.py
dytb/models/predefined/LeNet.py
dytb/models/predefined/LeNetBN.py
dytb/models/predefined/LeNetDirectDropout.py
dytb/models/predefined/LeNetDropout.py
dytb/models/predefined/SingleLayerCAE.py
dytb/models/predefined/StackedCAE.py
dytb/models/predefined/StackedDenoisingCAE.py
dytb/models/predefined/VGG.py
dytb/models/predefined/VGGBN.py
dytb/models/predefined/VGGDirectDropout.py
dytb/models/predefined/VGGDropout.py
dytb/models/predefined/__init__.py
dytb/trainer/Trainer.py
dytb/trainer/__init__.py
dytb/trainer/utils/__init__.py
dytb/trainer/utils/builders.py
dytb/trainer/utils/flow.py
dytb/utils/CLIArgs.py
dytb/utils/__init__.py
dytb-0.7.4.data/scripts/dytb_evaluate
dytb-0.7.4.data/scripts/dytb_train
dytb-0.7.4.dist-info/DESCRIPTION.rst
dytb-0.7.4.dist-info/METADATA
dytb-0.7.4.dist-info/RECORD
dytb-0.7.4.dist-info/WHEEL
dytb-0.7.4.dist-info/metadata.json
dytb-0.7.4.dist-info/top_level.txt
