Metadata-Version: 2.0
Name: dytb
Version: 0.7.4
Summary: Simplify the trainining and tuning of Tensorflow models
Home-page: https://github.com/galeone/dynamic-training-bench
Author: Paolo Galeone
Author-email: nessuno@nerdz.eu
License: MPL
Download-URL: https://github.com/galeone/dynamic-training-bench/tarball/0.7.4
Platform: UNKNOWN
